flaskmongorm/__init__.py
flaskmongorm-2024.8.23.dist-info/LICENSE
flaskmongorm-2024.8.23.dist-info/METADATA
flaskmongorm-2024.8.23.dist-info/WHEEL
flaskmongorm-2024.8.23.dist-info/top_level.txt
flaskmongorm-2024.8.23.dist-info/RECORD
