Metadata-Version: 2.1
Name: flaskmongorm
Version: 2024.8.23
Summary: Simple wrapper for flask-pymongo
Home-page: https://github.com/lixxu/flaskmongorm
Author: Lix Xu
Author-email: xuzenglin@gmail.com
License: BSD-3-Clause
Platform: any
Classifier: Environment :: Web Environment
Classifier: Intended Audience :: Developers
Classifier: License :: OSI Approved :: BSD License
Classifier: Operating System :: OS Independent
Classifier: Programming Language :: Python
Classifier: Topic :: Internet :: WWW/HTTP :: Dynamic Content
Classifier: Topic :: Software Development :: Libraries :: Python Modules
Classifier: Programming Language :: Python :: 3.7
Classifier: Programming Language :: Python :: 3.8
Classifier: Programming Language :: Python :: 3.9
Classifier: Programming Language :: Python :: 3.10
Classifier: Programming Language :: Python :: 3.11
License-File: LICENSE
Requires-Dist: flask-pymongo>=2.3.0
Requires-Dist: pymongo
Requires-Dist: tzdata
Requires-Dist: backports.zoneinfo; python_version < "3.9"
